MANIFEST.in
README.md
setup.py
pmail/__init__.py
pmail/__main__.py
pmail/client.py
pmail/common.py
pmail/config.yaml
pmail/sendmail.py
pmail/server.py
pmail/subscriber.py
pmail_tui.egg-info/PKG-INFO
pmail_tui.egg-info/SOURCES.txt
pmail_tui.egg-info/dependency_links.txt
pmail_tui.egg-info/requires.txt
pmail_tui.egg-info/top_level.txt